HyperFlow/Readme.md
HyperFlow/__init__.py
HyperFlow/src/FlowUnit_module.py
HyperFlow/src/Nuron.py
HyperFlow/src/__init__.py
HyperFlow_Package-1.0.0.dist-info/METADATA
HyperFlow_Package-1.0.0.dist-info/WHEEL
HyperFlow_Package-1.0.0.dist-info/top_level.txt
HyperFlow_Package-1.0.0.dist-info/RECORD
