Metadata-Version: 2.2
Name: HyperFlow_Package
Version: 1.0.0
Summary: HyperFlow: Next-Generation Computational Framework for Machine Learning & Deep Learning
Home-page: https://github.com/Shyanil/HyperFlow/tree/main/The%20HyperFlow/HyperFlow
Author: Shyanil Mishra
Author-email: shyanilmishra94@gmail.com
License: MIT
Requires-Python: >=3.8
Requires-Dist: numpy<2.1,>=1.26
Provides-Extra: dev
Requires-Dist: pytest>=7.0; extra == "dev"
Requires-Dist: twine>=4.0.2; extra == "dev"
Dynamic: author
Dynamic: author-email
Dynamic: description
Dynamic: description-content-type
Dynamic: home-page
Dynamic: provides-extra
Dynamic: requires-dist
Dynamic: requires-python
Dynamic: summary
